pollination/geojson_annual_energy_use/__init__.py
pollination/geojson_annual_energy_use/entry.py
pollination_geojson_annual_energy_use-0.2.1.dist-info/LICENSE
pollination_geojson_annual_energy_use-0.2.1.dist-info/METADATA
pollination_geojson_annual_energy_use-0.2.1.dist-info/WHEEL
pollination_geojson_annual_energy_use-0.2.1.dist-info/top_level.txt
pollination_geojson_annual_energy_use-0.2.1.dist-info/RECORD
